Workbook

Sheet Bookings_Data
A1: Booking_ID | B1: Booking_Date | C1: Category | D1: City | E1: Channel | F1: Base_Price | G1: Discount_% | H1: Final_Price | I1: Booking_Status | J1: Refund_Amount | K1: Net_Revenue | L1: Expected_Discount_% | M1: Discount Deviation
A2: 1 | B2: 45394 | C2: Packages | D2: Kolkata | E2: Paid Ads | F2: 35025 | G2: 0.11 | H2: 31286.72 | I2: Confirmed | J2: 0 | K2: =H2-J2 -> 31286.72 | L2: =VLOOKUP(C2,Helper_Data!$A$2:$B$4,2) -> 0.12 | M2: =G2-L2 -> -0.01
A3: 2 | B3: 45640 | C3: Hotels | D3: Delhi | E3: Organic | F3: 3546 | G3: 0.31 | H3: 2436.63 | I3: Cancelled | J3: 2071.14 | K3: =H3-J3 -> 365.49 | L3: =VLOOKUP(C3,Helper_Data!$A$2:$B$4,2) -> 0.08 | M3: =G3-L3 -> 0.23
A4: 3 | B4: 45562 | C4: Flights | D4: Mumbai | E4: Direct | F4: 6418 | G4: 0.08 | H4: 5903.09 | I4: Confirmed | J4: 0 | K4: =H4-J4 -> 5903.09 | L4: =VLOOKUP(C4,Helper_Data!$A$2:$B$4,2) -> 0.08 | M4: =G4-L4 -> 0
A5: 4 | B5: 45398 | C5: Flights | D5: Jaipur | E5: Affiliate | F5: 7245 | G5: 0.01 | H5: 7185.92 | I5: Confirmed | J5: 0 | K5: =H5-J5 -> 7185.92 | L5: =VLOOKUP(C5,Helper_Data!$A$2:$B$4,2) -> 0.08 | M5: =G5-L5 -> -0.07
A6: 5 | B6: 45363 | C6: Hotels | D6: Goa | E6: Direct | F6: 5283 | G6: 0.22 | H6: 4109.39 | I6: Cancelled | J6: 3492.98 | K6: =H6-J6 -> 616.41 | L6: =VLOOKUP(C6,Helper_Data!$A$2:$B$4,2) -> 0.08 | M6: =G6-L6 -> 0.14
A7: 6 | B7: 45480 | C7: Packages | D7: Kolkata | E7: Paid Ads | F7: 30267 | G7: 0.13 | H7: 26199.84 | I7: Confirmed | J7: 0 | K7: =H7-J7 -> 26199.84 | L7: =VLOOKUP(C7,Helper_Data!$A$2:$B$4,2) -> 0.12 | M7: =G7-L7 -> 0.01
A8: 7 | B8: 45312 | C8: Hotels | D8: Mumbai | E8: Direct | F8: 5598 | G8: 0.2 | H8: 4485.41 | I8: Confirmed | J8: 0 | K8: =H8-J8 -> 4485.41 | L8: =VLOOKUP(C8,Helper_Data!$A$2:$B$4,2) -> 0.08 | M8: =G8-L8 -> 0.12
A9: 8 | B9: 45394 | C9: Flights | D9: Jaipur | E9: Paid Ads | F9: 8303 | G9: 0.04 | H9: 7931.4 | I9: Confirmed | J9: 0 | K9: =H9-J9 -> 7931.4 | L9: =VLOOKUP(C9,Helper_Data!$A$2:$B$4,2) -> 0.08 | M9: =G9-L9 -> -0.04
A10: 9 | B10: 45413 | C10: Flights | D10: Delhi | E10: Paid Ads | F10: 11228 | G10: 0.02 | H10: 10960.27 | I10: Confirmed | J10: 0 | K10: =H10-J10 -> 10960.27 | L10: =VLOOKUP(C10,Helper_Data!$A$2:$B$4,2) -> 0.08 | M10: =G10-L10 -> -0.06
A11: 10 | B11: 45506 | C11: Flights | D11: Kolkata | E11: Organic | F11: 11017 | G11: 0.05 | H11: 10440.3 | I11: Confirmed | J11: 0 | K11: =H11-J11 -> 10440.3 | L11: =VLOOKUP(C11,Helper_Data!$A$2:$B$4,2) -> 0.08 | M11: =G11-L11 -> -0.03
A12: 11 | B12: 45622 | C12: Hotels | D12: Jaipur | E12: Organic | F12: 6238 | G12: 0.29 | H12: 4437.1 | I12: Confirmed | J12: 0 | K12: =H12-J12 -> 4437.1 | L12: =VLOOKUP(C12,Helper_Data!$A$2:$B$4,2) -> 0.08 | M12: =G12-L12 -> 0.21
A13: 12 | B13: 45379 | C13: Packages | D13: Goa | E13: Paid Ads | F13: 34513 | G13: 0.14 | H13: 29697.18 | I13: Confirmed | J13: 0 | K13: =H13-J13 -> 29697.18 | L13: =VLOOKUP(C13,Helper_Data!$A$2:$B$4,2) -> 0.12 | M13: =G13-L13 -> 0.02
... A30001: 30000 | B30001: 45599 | C30001: Hotels | D30001: Bangalore | E30001: Organic | F30001: 7492 | G30001: 0.32 | H30001: 5094.97 | I30001: Confirmed | J30001: 0 | K30001: =H30001-J30001 -> 5094.97 | L30001: =VLOOKUP(C30001,Helper_Data!$A$2:$B$4,2) -> 0.08 | M30001: =G30001-L30001 -> 0.24

Sheet Helper_Data
A1: Category | B1: Expected_Discount_% | C1: Expected_Cancel_%
A2: Hotels | B2: 0.18 | C2: 0.2
A3: Flights | B3: 0.08 | C3: 0.12
A4: Packages | B4: 0.12 | C4: 0.1
A6: Channel | B6: Cost_per_Booking
A7: Organic | B7: 50
A8: Paid Ads | B8: 420
A9: Affiliate | B9: 180
A10: Direct | B10: 30
A12: City | B12: City_Tier
A13: Delhi | B13: Tier 1
A14: Mumbai | B14: Tier 1
A15: Bangalore | B15: Tier 1
A16: Jaipur | B16: Tier 2
A17: Goa | B17: Tier 2
A18: Kolkata | B18: Tier 2
